pc_control/__init__.py
pc_control/bot.py
pc_control/config.py
pc_control/control.py
pc_control/utils.py
society_pc_control-0.1.0.dist-info/METADATA
society_pc_control-0.1.0.dist-info/WHEEL
society_pc_control-0.1.0.dist-info/top_level.txt
society_pc_control-0.1.0.dist-info/RECORD
