Metadata-Version: 2.1
Name: society_pc_control
Version: 0.1.0
Summary: Телеграм бот и библиотека для удаленного управления ПК (мышь, клавиатура)
Home-page: 
Author: fzcociety
Author-email: userexamplehx@gmail.com
Classifier: Programming Language :: Python :: 3
Classifier: License :: OSI Approved :: MIT License
Classifier: Operating System :: OS Independent
Requires-Python: >=3.8
Requires-Dist: pyTelegramBotAPI
Requires-Dist: pyautogui
Requires-Dist: pillow
Requires-Dist: opencv-python
Requires-Dist: numpy
Requires-Dist: python-dotenv
